README.rst
setup.py
errorpro/__init__.py
errorpro/core.py
errorpro/csv.py
errorpro/fitting.py
errorpro/interactive.py
errorpro/interpreter.py
errorpro/mean_value.py
errorpro/plotting_gnuplot.py
errorpro/plotting_matplotlib.py
errorpro/pytex.py
errorpro/quantities.py
errorpro/si.py
errorpro/units.py
errorpro.egg-info/PKG-INFO
errorpro.egg-info/SOURCES.txt
errorpro.egg-info/dependency_links.txt
errorpro.egg-info/top_level.txt
errorpro/dimensions/__init__.py
errorpro/dimensions/dimensions.py
errorpro/dimensions/simplifiers.py
errorpro/dimensions/solvers.py
errorpro/parsing/__init__.py
errorpro/parsing/generated.py
errorpro/parsing/parsing.py