Metadata-Version: 1.1
Name: errorpro
Version: 0.1.6
Summary: ErrorPro allows to do calculations in IPython with physical quantities, which contain a value, error and unit.
Home-page: http://github.com/lukasbk/ErrorPro
Author: Lukas Bentkamp
Author-email: lukas.bentkamp@mailbox.org
License: BSD
Download-URL: https://github.com/lukasbk/ErrorPro/tarball/0.1.5
Keywords: error uncertainty propagation units physics
Platform: UNKNOWN
Classifier: Development Status :: 3 - Alpha
Classifier: Topic :: Utilities
Classifier: Intended Audience :: Science/Research
Classifier: Topic :: Scientific/Engineering :: Physics
Classifier: License :: OSI Approved :: BSD License
